MANIFEST.in
README.rst
setup.py
ternpy/__init__.py
ternpy/command_line.py
ternpy/input_generator.py
ternpy/load_data.py
ternpy.egg-info/PKG-INFO
ternpy.egg-info/SOURCES.txt
ternpy.egg-info/dependency_links.txt
ternpy.egg-info/entry_points.txt
ternpy.egg-info/not-zip-safe
ternpy.egg-info/requires.txt
ternpy.egg-info/top_level.txt