Metadata-Version: 1.0
Name: ternpy
Version: 0.1.2
Summary: Ternary Plot Tool
Home-page: http://github.com/ad1v7/ternpy
Author: Marcin Kirsz
Author-email: marcin.kirsz@example.com
License: MIT
Platform: UNKNOWN
